MANIFEST.in
README.md
setup.cfg
setup.py
rest_meets_djongo/__init__.py
rest_meets_djongo/fields.py
rest_meets_djongo/kwarg_manager.py
rest_meets_djongo/meta_manager.py
rest_meets_djongo/serializers.py
rest_meets_djongo.egg-info/PKG-INFO
rest_meets_djongo.egg-info/SOURCES.txt
rest_meets_djongo.egg-info/dependency_links.txt
rest_meets_djongo.egg-info/not-zip-safe
rest_meets_djongo.egg-info/requires.txt
rest_meets_djongo.egg-info/top_level.txt