Metadata-Version: 2.1
Name: rest-meets-djongo
Version: 0.0.12.5
Summary: Allows for automatic serialization of Djongo fields w/ Django REST
Home-page: https://gitlab.com/SomeoneInParticular/rest_meets_djongo
Author: Kalum J. Ost
Author-email: kalumost@gmail.com
License: MIT
Keywords: mongodb djongo rest_framework rest apis fields
Platform: UNKNOWN
Classifier: Programming Language :: Python :: 3
Classifier: License :: OSI Approved :: MIT License
Classifier: Operating System :: OS Independent
